aiosubpub/__init__.py
aiosubpub/aiosubpub.py
aiosubpub/py.typed
aiosubpub-2.0.0.dist-info/LICENSE
aiosubpub-2.0.0.dist-info/WHEEL
aiosubpub-2.0.0.dist-info/METADATA
aiosubpub-2.0.0.dist-info/RECORD
