Metadata-Version: 2.1
Name: aiosubpub
Version: 2.0.0
Summary: Aio sub pub package.
Home-page: https://github.com/sander76/pypubsub
Author: Sander Teunissen
Author-email: no_mail@nomail.com
Requires-Python: >=3.7
Classifier: License :: OSI Approved :: MIT License
Requires-Dist: pytest-cov ; extra == "dev"
Requires-Dist: coverage[toml]>=5.0.3 ; extra == "dev"
Requires-Dist: pre-commit ; extra == "dev"
Requires-Dist: pylint ; extra == "dev"
Requires-Dist: pre-commit ; extra == "dev"
Requires-Dist: nox ; extra == "dev"
Requires-Dist: pytest ; extra == "test"
Requires-Dist: pytest-asyncio ; extra == "test"
Provides-Extra: dev
Provides-Extra: test
